consensus/__init__.py
consensus/base.py
consensus/core.py
consensus/logger.py
consensus/majority_vote.py
consensus/rank_aggregator.py
consensus/types.py
consensus/weighted_vote.py
llm_consensus-0.1.0.dist-info/licenses/LICENSE
llm_consensus-0.1.0.dist-info/METADATA
llm_consensus-0.1.0.dist-info/WHEEL
llm_consensus-0.1.0.dist-info/top_level.txt
llm_consensus-0.1.0.dist-info/RECORD
