Metadata-Version: 2.4
Name: llm_consensus
Version: 0.1.0
Summary: Langchain-compatible deliberation and consensus framework using multiple LLMs.
Author: Jeff Andrade
Author-email: Jeff Andrade <jersobh@gmail.com>
License: MIT
Project-URL: Homepage, https://github.com/jersobh/consensus
Project-URL: Repository, https://github.com/jersobh/consensus
Requires-Python: >=3.11
License-File: LICENSE
Requires-Dist: langchain
Requires-Dist: langchain_community
Requires-Dist: openai
Requires-Dist: transformers
Requires-Dist: torch
Requires-Dist: ollama
Dynamic: author
Dynamic: license-file
Dynamic: requires-python
